{
  "meta": {
    "title": "Играйте в Пасьянс Онлайн | Бесплатная карточная игра Пасьянс",
    "description": "Играйте в классический Пасьянс онлайн бесплатно! Наслаждайтесь этой вечной карточной игрой с удобным интерфейсом и красивым дизайном.",
    "keywords": "Пасьянс, бесплатная игра Пасьянс, играть в Пасьянс, онлайн Пасьянс, карточные игры, классический Пасьянс, Клондайк, игра в терпение"
  },
  "header": {
    "btn": {
      "reset": "Новая игра",
      "resetScore": "Сбросить счёт"
    },
    "score": "Счёт: {score}"
  },
  "content": {
    "win": {
      "text": "Вы выиграли!"
    },
    "loading": "Загрузка"
  },
  "cookies": {
    "text": "Мы используем файлы cookie, чтобы улучшить ваш опыт. Принимая, вы соглашаетесь с использованием файлов cookie.",
    "accept": "Принять",
    "decline": "Отклонить"
  }
}
